solc_simple/__init__.py
solc_simple/builder.py
py_solc_simple-0.0.14.dist-info/LICENSE
py_solc_simple-0.0.14.dist-info/METADATA
py_solc_simple-0.0.14.dist-info/WHEEL
py_solc_simple-0.0.14.dist-info/entry_points.txt
py_solc_simple-0.0.14.dist-info/top_level.txt
py_solc_simple-0.0.14.dist-info/RECORD
