Metadata-Version: 2.1
Name: py-solc-simple
Version: 0.0.14
Summary: Simple wrapper around py-solc-x. Needs solc binary in PATH
Home-page: https://github.com/omisego/py-solc-simple
Author: Paul Peregud
Author-email: paulperegud@gmail.com
License: UNKNOWN
Platform: UNKNOWN
Classifier: Intended Audience :: Developers
Classifier: Programming Language :: Python :: 3
Classifier: License :: OSI Approved :: MIT License
Classifier: Operating System :: OS Independent
Requires-Dist: py-solc-x (==0.4.0)
Provides-Extra: test
Requires-Dist: pytest (>=4.4.0) ; extra == 'test'
